<?xml version="1.0" encoding="UTF-8" ?>
<class name="PCKSceneTree" inherits="SceneTree" version="4.0" xmlns:xsi="http://www.w3.org/2001/XMLSchema-instance" xsi:noNamespaceSchemaLocation="../../../doc/class.xsd">
	<brief_description>
		A mainloop type to for [PCKRunner].
	</brief_description>
	<description>
		PCK file of another game can be launch by [PCKRunner]. When the game call [method SceneTree.quit], the application will not stop but return to previus scene.
	</description>
	<tutorials>
	</tutorials>
	<signals>
		<signal name="__pck_quited">
			<description>
			</description>
		</signal>
	</signals>
</class>
